LICENSE
MANIFEST.in
README.rst
setup.py
simocollector/__init__.py
simocollector/collectors.py
simocollector/sample_config.py
simocollector/sender.py
simocollector/utils.py
simocollector.egg-info/PKG-INFO
simocollector.egg-info/SOURCES.txt
simocollector.egg-info/dependency_links.txt
simocollector.egg-info/requires.txt
simocollector.egg-info/top_level.txt
simocollector/bin/create-simo-config.py
simocollector/bin/install-simocollection.py
simocollector/bin/simo-collection-publish.py