Metadata-Version: 1.1
Name: simocollector
Version: 1.2.2
Summary: SIMO Collector
Home-page: https://github.com/rbas/simocollector
Author: Martin Voldrich
Author-email: rbas.cz@gmail.com
License: Copyright (c) 2014, Martin Voldrich <rbas.cz@gmail.com>
